{
    "modes": {
        "installed-extensions": {
            "name": "Zed Search Results",
            "highlighter": "ace/mode/markdown",
            "filenames": ["zed::zpm::installed"],

            "keys": {
                "Installed Extensions:Execute Command": "Enter"
            },

            "commands": {
                "Installed Extensions:Execute Command": {
                    "scriptUrl": "/default/mode/installed-extensions/execute.js"
                }
            },

            "preferences": {
                "showGutter": false,
                "showPrintMargin": false
            }
        }
    }
}